reflexive/__init__.py
reflexive/analysis_functions.py
reflexive/display_functions.py
reflexive/res_analysis.py
reflexive/service.py
reflexive-2.2.2.dist-info/METADATA
reflexive-2.2.2.dist-info/WHEEL
reflexive-2.2.2.dist-info/licenses/LICENSE
reflexive-2.2.2.dist-info/RECORD
