Metadata-Version: 2.4
Name: reflexive
Version: 2.2.2
Summary: Supports AWS Reflexive Expressions Systems (RES) Analysis
Project-URL: Repository, https://github.com/nlytx/reflexive.git
Author-email: Andrew Gibson <andrew@nlytx.io>
License-File: LICENSE
Classifier: Development Status :: 4 - Beta
Classifier: License :: OSI Approved :: Apache Software License
Classifier: Operating System :: OS Independent
Classifier: Programming Language :: Python :: 3
Requires-Python: >=3.11
